ssh_cert_parser/__init__.py
ssh_cert_parser/__version__.py
ssh_cert_parser/algs.py
ssh_cert_parser/cli.py
ssh_cert_parser/core.py
ssh_cert_parser/decoder.py
ssh_cert_parser/vars.py
ssh_cert_parser-0.1.post3817469255.dist-info/LICENSE
ssh_cert_parser-0.1.post3817469255.dist-info/METADATA
ssh_cert_parser-0.1.post3817469255.dist-info/WHEEL
ssh_cert_parser-0.1.post3817469255.dist-info/entry_points.txt
ssh_cert_parser-0.1.post3817469255.dist-info/top_level.txt
ssh_cert_parser-0.1.post3817469255.dist-info/zip-safe
ssh_cert_parser-0.1.post3817469255.dist-info/RECORD
