Metadata-Version: 2.1
Name: ssh-cert-parser
Version: 0.1.post3817469255
Summary: A python module for parsing OpenSSH certificates
Home-page: https://github.com/scheibling/ssh-cert-parser
Author: Lars Scheibling
Author-email: lars@scheibling.se
License: GnuPG 3.0
Keywords: python openssh ssh-certificate certificate parser decoder
Classifier: Programming Language :: Python :: 3
Classifier: License :: OSI Approved :: GNU General Public License v3 (GPLv3)
Classifier: Operating System :: OS Independent
Requires-Python: >=3.6
License-File: LICENSE
Requires-Dist: click
